qmsolver/__init__.py
qmsolver/potentials/__init__.py
qmsolver/potentials/base.py
qmsolver/potentials/double_square_well.py
qmsolver/potentials/finite_square_well.py
qmsolver/potentials/harmonic_oscillator.py
qmsolver/potentials/multiple_square_well.py
qmsolver/potentials/poschl_teller.py
qmsolver/tise/__init__.py
qmsolver/tise/finite_differences.py
qmsolver-0.1.4.dist-info/licenses/LICENSE
qmsolver-0.1.4.dist-info/METADATA
qmsolver-0.1.4.dist-info/WHEEL
qmsolver-0.1.4.dist-info/top_level.txt
qmsolver-0.1.4.dist-info/RECORD
