Metadata-Version: 2.4
Name: qmsolver
Version: 0.1.4
Summary: A quantum mechanics solver library
Author-email: Georgios Batagiannis <gbatagian@gmail.com>
License-Expression: MIT
Project-URL: Homepage, https://github.com/gbatagian/qmsolver
Project-URL: Repository, https://github.com/gbatagian/qmsolver
Project-URL: Documentation, https://github.com/gbatagian/qmsolver#readme
Classifier: Programming Language :: Python :: 3
Classifier: Programming Language :: Python :: 3.9
Classifier: Programming Language :: Python :: 3.10
Classifier: Programming Language :: Python :: 3.11
Classifier: Programming Language :: Python :: 3.12
Classifier: Programming Language :: Python :: 3.13
Classifier: Operating System :: OS Independent
Classifier: Topic :: Scientific/Engineering :: Physics
Requires-Python: >=3.9
License-File: LICENSE
Requires-Dist: numpy
Requires-Dist: scipy
Requires-Dist: matplotlib
Dynamic: license-file
